golinux/__init__.py
golinux/core.py
golinux-1.0.3.dist-info/METADATA
golinux-1.0.3.dist-info/WHEEL
golinux-1.0.3.dist-info/top_level.txt
golinux-1.0.3.dist-info/RECORD
